bebop_finger/__init__.py
bebop_finger/plugin.py
bebop_browser_finger-0.1.0.dist-info/METADATA
bebop_browser_finger-0.1.0.dist-info/WHEEL
bebop_browser_finger-0.1.0.dist-info/top_level.txt
bebop_browser_finger-0.1.0.dist-info/RECORD
